ITR/__init__.py
ITR/configs.py
ITR/data/__init__.py
ITR/data/base_providers.py
ITR/data/data_providers.py
ITR/data/data_warehouse.py
ITR/data/excel.py
ITR/data/input/country_region_info.csv
ITR/data/input/oecd_iso.csv
ITR/data/input/region_classification.csv
ITR/data/json/benchmark_EI_OECM.json
ITR/data/json/benchmark_EI_OECM_PC.json
ITR/data/json/benchmark_EI_OECM_S3.json
ITR/data/json/benchmark_EI_S3.json
ITR/data/json/benchmark_EI_TPI_1_5_degrees.json
ITR/data/json/benchmark_EI_TPI_2_degrees.json
ITR/data/json/benchmark_EI_TPI_2_degrees_high_efficiency.json
ITR/data/json/benchmark_EI_TPI_2_degrees_shift_improve.json
ITR/data/json/benchmark_EI_TPI_below_2_degrees.json
ITR/data/json/benchmark_production_OECM.json
ITR/data/osc_units.py
ITR/data/template.py
ITR/data/vault_providers.py
ITR/interfaces.py
ITR/portfolio_aggregation.py
ITR/py.typed
ITR/temperature_score.py
ITR/utils.py
itr-1.1.10.dist-info/METADATA
itr-1.1.10.dist-info/WHEEL
itr-1.1.10.dist-info/entry_points.txt
itr-1.1.10.dist-info/licenses/LICENSE.txt
itr-1.1.10.dist-info/RECORD
